<?xml version="1.0" encoding="UTF-8"?>
<!DOCTYPE mapper PUBLIC "-//mybatis.org//DTD Mapper 3.0//EN" "http://mybatis.org/dtd/mybatis-3-mapper.dtd">
<mapper namespace="com.wnn.springboot.dao.SysUserMapper">
  <resultMap id="BaseResultMap" type="com.wnn.springboot.model.SysUser">
    <!--
      WARNING - @mbggenerated
      This element is automatically generated by MyBatis Generator, do not modify.
    -->
    <result column="USER_ID" jdbcType="VARCHAR" property="userId" />
    <result column="USER_NAME" jdbcType="VARCHAR" property="userName" />
    <result column="LOGIN_PSW" jdbcType="VARCHAR" property="loginPsw" />
    <result column="GROUP_CODE" jdbcType="VARCHAR" property="groupCode" />
    <result column="ROLE_CODE" jdbcType="VARCHAR" property="roleCode" />
    <result column="POST" jdbcType="VARCHAR" property="post" />
    <result column="OFFICE" jdbcType="VARCHAR" property="office" />
    <result column="TELEPHONE_NO" jdbcType="VARCHAR" property="telephoneNo" />
    <result column="EMAIL_ADDRESS" jdbcType="VARCHAR" property="emailAddress" />
    <result column="FAX_NO" jdbcType="VARCHAR" property="faxNo" />
    <result column="BRANCH_CODE" jdbcType="VARCHAR" property="branchCode" />
    <result column="CREATED_USER" jdbcType="VARCHAR" property="createdUser" />
    <result column="CREATED_DATE" jdbcType="TIMESTAMP" property="createdDate" />
    <result column="LAST_UPD_USER" jdbcType="VARCHAR" property="lastUpdUser" />
    <result column="LAST_UPD_DATE" jdbcType="TIMESTAMP" property="lastUpdDate" />
    <result column="ACTIVE_IND" jdbcType="VARCHAR" property="activeInd" />
    <result column="CHG_PWD_DATE" jdbcType="TIMESTAMP" property="chgPwdDate" />
    <result column="FAILED_COUNT" jdbcType="VARCHAR" property="failedCount" />
    <result column="LAST_FAILEDDATE" jdbcType="TIMESTAMP" property="lastFaileddate" />
    <result column="REQ_CHANGEPWD_IND" jdbcType="VARCHAR" property="reqChangepwdInd" />
  </resultMap>
  <insert id="insert" parameterType="com.wnn.springboot.model.SysUser">
    <!--
      WARNING - @mbggenerated
      This element is automatically generated by MyBatis Generator, do not modify.
    -->
    insert into sys_user (USER_ID, USER_NAME, LOGIN_PSW, 
      GROUP_CODE, ROLE_CODE, POST, 
      OFFICE, TELEPHONE_NO, EMAIL_ADDRESS, 
      FAX_NO, BRANCH_CODE, CREATED_USER, 
      CREATED_DATE, LAST_UPD_USER, LAST_UPD_DATE, 
      ACTIVE_IND, CHG_PWD_DATE, FAILED_COUNT, 
      LAST_FAILEDDATE, REQ_CHANGEPWD_IND)
    values (#{userId,jdbcType=VARCHAR}, #{userName,jdbcType=VARCHAR}, #{loginPsw,jdbcType=VARCHAR}, 
      #{groupCode,jdbcType=VARCHAR}, #{roleCode,jdbcType=VARCHAR}, #{post,jdbcType=VARCHAR}, 
      #{office,jdbcType=VARCHAR}, #{telephoneNo,jdbcType=VARCHAR}, #{emailAddress,jdbcType=VARCHAR}, 
      #{faxNo,jdbcType=VARCHAR}, #{branchCode,jdbcType=VARCHAR}, #{createdUser,jdbcType=VARCHAR}, 
      #{createdDate,jdbcType=TIMESTAMP}, #{lastUpdUser,jdbcType=VARCHAR}, #{lastUpdDate,jdbcType=TIMESTAMP}, 
      #{activeInd,jdbcType=VARCHAR}, #{chgPwdDate,jdbcType=TIMESTAMP}, #{failedCount,jdbcType=VARCHAR}, 
      #{lastFaileddate,jdbcType=TIMESTAMP}, #{reqChangepwdInd,jdbcType=VARCHAR})
  </insert>
  <insert id="insertSelective" parameterType="com.wnn.springboot.model.SysUser">
    <!--
      WARNING - @mbggenerated
      This element is automatically generated by MyBatis Generator, do not modify.
    -->
    insert into sys_user
    <trim prefix="(" suffix=")" suffixOverrides=",">
      <if test="userId != null">
        USER_ID,
      </if>
      <if test="userName != null">
        USER_NAME,
      </if>
      <if test="loginPsw != null">
        LOGIN_PSW,
      </if>
      <if test="groupCode != null">
        GROUP_CODE,
      </if>
      <if test="roleCode != null">
        ROLE_CODE,
      </if>
      <if test="post != null">
        POST,
      </if>
      <if test="office != null">
        OFFICE,
      </if>
      <if test="telephoneNo != null">
        TELEPHONE_NO,
      </if>
      <if test="emailAddress != null">
        EMAIL_ADDRESS,
      </if>
      <if test="faxNo != null">
        FAX_NO,
      </if>
      <if test="branchCode != null">
        BRANCH_CODE,
      </if>
      <if test="createdUser != null">
        CREATED_USER,
      </if>
      <if test="createdDate != null">
        CREATED_DATE,
      </if>
      <if test="lastUpdUser != null">
        LAST_UPD_USER,
      </if>
      <if test="lastUpdDate != null">
        LAST_UPD_DATE,
      </if>
      <if test="activeInd != null">
        ACTIVE_IND,
      </if>
      <if test="chgPwdDate != null">
        CHG_PWD_DATE,
      </if>
      <if test="failedCount != null">
        FAILED_COUNT,
      </if>
      <if test="lastFaileddate != null">
        LAST_FAILEDDATE,
      </if>
      <if test="reqChangepwdInd != null">
        REQ_CHANGEPWD_IND,
      </if>
    </trim>
    <trim prefix="values (" suffix=")" suffixOverrides=",">
      <if test="userId != null">
        #{userId,jdbcType=VARCHAR},
      </if>
      <if test="userName != null">
        #{userName,jdbcType=VARCHAR},
      </if>
      <if test="loginPsw != null">
        #{loginPsw,jdbcType=VARCHAR},
      </if>
      <if test="groupCode != null">
        #{groupCode,jdbcType=VARCHAR},
      </if>
      <if test="roleCode != null">
        #{roleCode,jdbcType=VARCHAR},
      </if>
      <if test="post != null">
        #{post,jdbcType=VARCHAR},
      </if>
      <if test="office != null">
        #{office,jdbcType=VARCHAR},
      </if>
      <if test="telephoneNo != null">
        #{telephoneNo,jdbcType=VARCHAR},
      </if>
      <if test="emailAddress != null">
        #{emailAddress,jdbcType=VARCHAR},
      </if>
      <if test="faxNo != null">
        #{faxNo,jdbcType=VARCHAR},
      </if>
      <if test="branchCode != null">
        #{branchCode,jdbcType=VARCHAR},
      </if>
      <if test="createdUser != null">
        #{createdUser,jdbcType=VARCHAR},
      </if>
      <if test="createdDate != null">
        #{createdDate,jdbcType=TIMESTAMP},
      </if>
      <if test="lastUpdUser != null">
        #{lastUpdUser,jdbcType=VARCHAR},
      </if>
      <if test="lastUpdDate != null">
        #{lastUpdDate,jdbcType=TIMESTAMP},
      </if>
      <if test="activeInd != null">
        #{activeInd,jdbcType=VARCHAR},
      </if>
      <if test="chgPwdDate != null">
        #{chgPwdDate,jdbcType=TIMESTAMP},
      </if>
      <if test="failedCount != null">
        #{failedCount,jdbcType=VARCHAR},
      </if>
      <if test="lastFaileddate != null">
        #{lastFaileddate,jdbcType=TIMESTAMP},
      </if>
      <if test="reqChangepwdInd != null">
        #{reqChangepwdInd,jdbcType=VARCHAR},
      </if>
    </trim>
  </insert>
</mapper>